microapp/__init__.py
microapp/__main__.py
microapp/app.py
microapp/base.py
microapp/error.py
microapp/framework.py
microapp/group.py
microapp/manage.py
microapp/mgmtapp.py
microapp/parallel.py
microapp/parse.py
microapp/project.py
microapp/script.py
microapp/stdapp.py
microapp/utils.py
microapp-0.3.15.dist-info/LICENSE
microapp-0.3.15.dist-info/METADATA
microapp-0.3.15.dist-info/WHEEL
microapp-0.3.15.dist-info/entry_points.txt
microapp-0.3.15.dist-info/top_level.txt
microapp-0.3.15.dist-info/RECORD
